atmo_desktop/Device.py
atmo_desktop/SplashScreen.py
atmo_desktop/__init__.py
atmo_desktop/atmoSniffer.py
atmo_desktop/dynamicDevice.py
atmo_desktop/loadingScreen.py
atmo_desktop/setup.py
atmo_desktop/setup_executable.py
atmo_desktop/versionParsing.py
atmo_desktop-0.0.1.dist-info/METADATA
atmo_desktop-0.0.1.dist-info/WHEEL
atmo_desktop-0.0.1.dist-info/top_level.txt
atmo_desktop-0.0.1.dist-info/RECORD
