Metadata-Version: 2.1
Name: atmo-desktop
Version: 0.0.1
Summary: Reading Atmosniffer device data.
Home-page: UNKNOWN
Author: Miguel Castrejon
Author-email: <miguelcastrejon@mail.weber.edu.com>
License: UNKNOWN
Keywords: python,atmoSniffer
Platform: UNKNOWN
Classifier: Programming Language :: Python :: 3
Classifier: Operating System :: Unix
Classifier: Operating System :: Microsoft :: Windows
Requires-Dist: PyQt5
Requires-Dist: serial
Requires-Dist: webbrowser
Requires-Dist: pandas
Requires-Dist: csv
Requires-Dist: os
Requires-Dist: cx-Freeze
Requires-Dist: matplotlib
Requires-Dist: io
Requires-Dist: datetime
